Janome-0.4.2.data/scripts/janome
Janome-0.4.2.data/scripts/janome.bat
janome/__init__.py
janome/analyzer.py
janome/charfilter.py
janome/dic.py
janome/fst.py
janome/lattice.py
janome/progress.py
janome/system_dic.py
janome/tokenfilter.py
janome/tokenizer.py
janome/version.py
janome/sysdic/__init__.py
janome/sysdic/chardef.py
janome/sysdic/connections1.py
janome/sysdic/connections2.py
janome/sysdic/entries_buckets.py
janome/sysdic/entries_compact0.py
janome/sysdic/entries_compact0_idx.py
janome/sysdic/entries_compact1.py
janome/sysdic/entries_compact1_idx.py
janome/sysdic/entries_compact2.py
janome/sysdic/entries_compact2_idx.py
janome/sysdic/entries_compact3.py
janome/sysdic/entries_compact3_idx.py
janome/sysdic/entries_compact4.py
janome/sysdic/entries_compact4_idx.py
janome/sysdic/entries_compact5.py
janome/sysdic/entries_compact5_idx.py
janome/sysdic/entries_compact6.py
janome/sysdic/entries_compact6_idx.py
janome/sysdic/entries_compact7.py
janome/sysdic/entries_compact7_idx.py
janome/sysdic/entries_compact8.py
janome/sysdic/entries_compact8_idx.py
janome/sysdic/entries_compact9.py
janome/sysdic/entries_compact9_idx.py
janome/sysdic/entries_extra0.py
janome/sysdic/entries_extra0_idx.py
janome/sysdic/entries_extra1.py
janome/sysdic/entries_extra1_idx.py
janome/sysdic/entries_extra2.py
janome/sysdic/entries_extra2_idx.py
janome/sysdic/entries_extra3.py
janome/sysdic/entries_extra3_idx.py
janome/sysdic/entries_extra4.py
janome/sysdic/entries_extra4_idx.py
janome/sysdic/entries_extra5.py
janome/sysdic/entries_extra5_idx.py
janome/sysdic/entries_extra6.py
janome/sysdic/entries_extra6_idx.py
janome/sysdic/entries_extra7.py
janome/sysdic/entries_extra7_idx.py
janome/sysdic/entries_extra8.py
janome/sysdic/entries_extra8_idx.py
janome/sysdic/entries_extra9.py
janome/sysdic/entries_extra9_idx.py
janome/sysdic/fst_data0.py
janome/sysdic/fst_data1.py
janome/sysdic/unknowns.py
Janome-0.4.2.dist-info/LICENSE.txt
Janome-0.4.2.dist-info/METADATA
Janome-0.4.2.dist-info/NOTICE.txt
Janome-0.4.2.dist-info/WHEEL
Janome-0.4.2.dist-info/top_level.txt
Janome-0.4.2.dist-info/RECORD
