Metadata-Version: 1.1
Name: Janome
Version: 0.4.2
Summary: Japanese morphological analysis engine.
Home-page: https://mocobeta.github.io/janome/en/
Author: Tomoko Uchida
Author-email: tomoko.uchida.1111@gmail.com
License: AL2
Platform: UNKNOWN
Classifier: Development Status :: 4 - Beta
Classifier: License :: OSI Approved :: Apache Software License
Classifier: Natural Language :: Japanese
Classifier: Programming Language :: Python :: 3.7
Classifier: Programming Language :: Python :: 3.8
Classifier: Programming Language :: Python :: 3.9
Classifier: Programming Language :: Python :: 3.10
